[
  {
    "fund_id": "PE047",
    "filing_type": "AIFMD",
    "filing_date": "2024-09-15",
    "filing_quarter": "2024-Q3",
    "reported_aum_millions": 2161.96,
    "reported_strategy": "Distressed",
    "num_investors": 138,
    "source": "ESMA"
  },
  {
    "fund_id": "PE047",
    "filing_type": "AIFMD",
    "filing_date": "2024-09-15",
    "filing_quarter": "2024-Q3",
    "reported_aum_millions": 3178.34,
    "reported_strategy": "Distressed",
    "num_investors": 10,
    "source": "SEC EDGAR"
  },
  {
    "fund_id": "HF006",
    "filing_type": "Form ADV",
    "filing_date": "2024-05-15",
    "filing_quarter": "2024-Q2",
    "reported_aum_millions": 10918.24,
    "reported_strategy": "Quantitative",
    "num_investors": 304,
    "source": "SEC EDGAR"
  },
  {
    "fund_id": "HF006",
    "filing_type": "Form ADV",
    "filing_date": "2023-11-15",
    "filing_quarter": "2023-Q4",
    "reported_aum_millions": 12981.33,
    "reported_strategy": "Quantitative",
    "num_investors": 233,
    "source": "ESMA"
  },
  {
    "fund_id": "VC021",
    "filing_type": "AIFMD",
    "filing_date": "2023-11-15",
    "filing_quarter": "2023-Q4",
    "reported_aum_millions": 1378.62,
    "reported_strategy": "Late Stage",
    "num_investors": 428,
    "source": "ESMA"
  },
  {
    "fund_id": "PE003",
    "filing_type": "Form ADV",
    "filing_date": "2023-11-15",
    "filing_quarter": "2023-Q4",
    "reported_aum_millions": 5004.43,
    "reported_strategy": "Early Stage",
    "num_investors": 359,
    "source": "ESMA"
  },
  {
    "fund_id": "VC037",
    "filing_type": "Form PF",
    "filing_date": "2024-09-15",
    "filing_quarter": "2024-Q3",
    "reported_aum_millions": 230.31,
    "reported_strategy": "Seed",
    "num_investors": 197,
    "source": "FCA"
  },
  {
    "fund_id": "VC037",
    "filing_type": "Form ADV",
    "filing_date": "2024-05-15",
    "filing_quarter": "2024-Q2",
    "reported_aum_millions": 213.1,
    "reported_strategy": "Seed",
    "num_investors": 341,
    "source": "SEC EDGAR"
  },
  {
    "fund_id": "PE018",
    "filing_type": "Form PF",
    "filing_date": "2023-11-15",
    "filing_quarter": "2023-Q4",
    "reported_aum_millions": 2628.86,
    "reported_strategy": "Buyout",
    "num_investors": 163,
    "source": "FCA"
  },
  {
    "fund_id": "PE004",
    "filing_type": "Form PF",
    "filing_date": "2024-09-15",
    "filing_quarter": "2024-Q3",
    "reported_aum_millions": 1344.09,
    "reported_strategy": "Mezzanine",
    "num_investors": 463,
    "source": "FCA"
  },
  {
    "fund_id": "PE004",
    "filing_type": "Form PF",
    "filing_date": "2024-02-15",
    "filing_quarter": "2024-Q1",
    "reported_aum_millions": 1314.19,
    "reported_strategy": "Quantitative",
    "num_investors": 22,
    "source": "FCA"
  },
  {
    "fund_id": "HF031",
    "filing_type": "AIFMD",
    "filing_date": "2024-02-15",
    "filing_quarter": "2024-Q1",
    "reported_aum_millions": 10952.08,
    "reported_strategy": "Quantitative",
    "num_investors": 167,
    "source": "ESMA"
  },
  {
    "fund_id": "PE026",
    "filing_type": "AIFMD",
    "filing_date": "2024-09-15",
    "filing_quarter": "2024-Q3",
    "reported_aum_millions": 477.98,
    "reported_strategy": "Buyout",
    "num_investors": 31,
    "source": "ESMA"
  },
  {
    "fund_id": "PE026",
    "filing_type": "AIFMD",
    "filing_date": "2024-09-15",
    "filing_quarter": "2024-Q3",
    "reported_aum_millions": 832.47,
    "reported_strategy": "Buyout",
    "num_investors": 244,
    "source": "FCA"
  },
  {
    "fund_id": "VC015",
    "filing_type": "AIFMD",
    "filing_date": "2023-11-15",
    "filing_quarter": "2023-Q4",
    "reported_aum_millions": 1235.58,
    "reported_strategy": "Mezzanine",
    "num_investors": 82,
    "source": "ESMA"
  },
  {
    "fund_id": "PE027",
    "filing_type": "Form PF",
    "filing_date": "2024-02-15",
    "filing_quarter": "2024-Q1",
    "reported_aum_millions": 4306.32,
    "reported_strategy": "Mezzanine",
    "num_investors": 369,
    "source": "FCA"
  },
  {
    "fund_id": "HF040",
    "filing_type": "Form ADV",
    "filing_date": "2024-09-15",
    "filing_quarter": "2024-Q3",
    "reported_aum_millions": 8001.67,
    "reported_strategy": "Multi-Strategy",
    "num_investors": 430,
    "source": "SEC EDGAR"
  },
  {
    "fund_id": "HF015",
    "filing_type": "Form PF",
    "filing_date": "2023-11-15",
    "filing_quarter": "2023-Q4",
    "reported_aum_millions": 2087.55,
    "reported_strategy": "Event Driven",
    "num_investors": 68,
    "source": "ESMA"
  },
  {
    "fund_id": "HF015",
    "filing_type": "Form PF",
    "filing_date": "2023-11-15",
    "filing_quarter": "2023-Q4",
    "reported_aum_millions": 1891.46,
    "reported_strategy": "Event Driven",
    "num_investors": 228,
    "source": "ESMA"
  },
  {
    "fund_id": "PE057",
    "filing_type": "AIFMD",
    "filing_date": "2024-05-15",
    "filing_quarter": "2024-Q2",
    "reported_aum_millions": 2116.11,
    "reported_strategy": "Buyout",
    "num_investors": 80,
    "source": "ESMA"
  },
  {
    "fund_id": "PE057",
    "filing_type": "Form ADV",
    "filing_date": "2024-08-15",
    "filing_quarter": "2024-Q3",
    "reported_aum_millions": 2139.39,
    "reported_strategy": "Buyout",
    "num_investors": 42,
    "source": "SEC EDGAR"
  },
  {
    "fund_id": "PE073",
    "filing_type": "Form ADV",
    "filing_date": "2024-08-15",
    "filing_quarter": "2024-Q3",
    "reported_aum_millions": 3215.37,
    "reported_strategy": "Growth Equity",
    "num_investors": 293,
    "source": "SEC EDGAR"
  },
  {
    "fund_id": "PE073",
    "filing_type": "Form PF",
    "filing_date": "2024-02-15",
    "filing_quarter": "2024-Q1",
    "reported_aum_millions": 3543.9,
    "reported_strategy": "Growth Equity",
    "num_investors": 61,
    "source": "FCA"
  },
  {
    "fund_id": "PE065",
    "filing_type": "Form PF",
    "filing_date": "2024-08-15",
    "filing_quarter": "2024-Q3",
    "reported_aum_millions": 4368.36,
    "reported_strategy": "Distressed",
    "num_investors": 13,
    "source": "SEC EDGAR"
  },
  {
    "fund_id": "PE065",
    "filing_type": "Form ADV",
    "filing_date": "2024-09-15",
    "filing_quarter": "2024-Q3",
    "reported_aum_millions": 4455.76,
    "reported_strategy": "Distressed",
    "num_investors": 223,
    "source": "FCA"
  },
  {
    "fund_id": "PE050",
    "filing_type": "AIFMD",
    "filing_date": "2024-08-15",
    "filing_quarter": "2024-Q3",
    "reported_aum_millions": 4512.01,
    "reported_strategy": "Mezzanine",
    "num_investors": 240,
    "source": "ESMA"
  },
  {
    "fund_id": "PE050",
    "filing_type": "Form PF",
    "filing_date": "2024-08-15",
    "filing_quarter": "2024-Q3",
    "reported_aum_millions": 4102.93,
    "reported_strategy": "Mezzanine",
    "num_investors": 315,
    "source": "SEC EDGAR"
  },
  {
    "fund_id": "PE009",
    "filing_type": "Form ADV",
    "filing_date": "2023-11-15",
    "filing_quarter": "2023-Q4",
    "reported_aum_millions": 3784.26,
    "reported_strategy": "Distressed",
    "num_investors": 188,
    "source": "ESMA"
  },
  {
    "fund_id": "PE009",
    "filing_type": "AIFMD",
    "filing_date": "2024-09-15",
    "filing_quarter": "2024-Q3",
    "reported_aum_millions": 3621.6,
    "reported_strategy": "Distressed",
    "num_investors": 58,
    "source": "FCA"
  },
  {
    "fund_id": "PE007",
    "filing_type": "AIFMD",
    "filing_date": "2023-11-15",
    "filing_quarter": "2023-Q4",
    "reported_aum_millions": 3079.46,
    "reported_strategy": "Buyout",
    "num_investors": 347,
    "source": "SEC EDGAR"
  },
  {
    "fund_id": "PE007",
    "filing_type": "Form PF",
    "filing_date": "2024-05-15",
    "filing_quarter": "2024-Q2",
    "reported_aum_millions": 2132.9,
    "reported_strategy": "Buyout",
    "num_investors": 360,
    "source": "ESMA"
  },
  {
    "fund_id": "PE024",
    "filing_type": "Form PF",
    "filing_date": "2024-08-15",
    "filing_quarter": "2024-Q3",
    "reported_aum_millions": -2007.21,
    "reported_strategy": "Distressed",
    "num_investors": 340,
    "source": "ESMA"
  },
  {
    "fund_id": "PE024",
    "filing_type": "AIFMD",
    "filing_date": "2024-05-15",
    "filing_quarter": "2024-Q2",
    "reported_aum_millions": -1201.66,
    "reported_strategy": "Distressed",
    "num_investors": 422,
    "source": "ESMA"
  },
  {
    "fund_id": "PE015",
    "filing_type": "Form PF",
    "filing_date": "2024-09-15",
    "filing_quarter": "2024-Q3",
    "reported_aum_millions": 843.14,
    "reported_strategy": "Buyout",
    "num_investors": 90,
    "source": "SEC EDGAR"
  },
  {
    "fund_id": "PE056",
    "filing_type": "AIFMD",
    "filing_date": "2023-11-15",
    "filing_quarter": "2023-Q4",
    "reported_aum_millions": 5808.62,
    "reported_strategy": "Growth Equity",
    "num_investors": 237,
    "source": "FCA"
  },
  {
    "fund_id": "PE056",
    "filing_type": "AIFMD",
    "filing_date": "2023-11-15",
    "filing_quarter": "2023-Q4",
    "reported_aum_millions": 4280.67,
    "reported_strategy": "Growth Equity",
    "num_investors": 469,
    "source": "ESMA"
  },
  {
    "fund_id": "PE032",
    "filing_type": "AIFMD",
    "filing_date": "2024-09-15",
    "filing_quarter": "2024-Q3",
    "reported_aum_millions": 2362.54,
    "reported_strategy": "Multi-Strategy",
    "num_investors": 221,
    "source": "SEC EDGAR"
  },
  {
    "fund_id": "PE031",
    "filing_type": "Form PF",
    "filing_date": "2024-08-15",
    "filing_quarter": "2024-Q3",
    "reported_aum_millions": 5340.37,
    "reported_strategy": "Distressed",
    "num_investors": 465,
    "source": "ESMA"
  },
  {
    "fund_id": "PE031",
    "filing_type": "Form PF",
    "filing_date": "2024-08-15",
    "filing_quarter": "2024-Q3",
    "reported_aum_millions": 5437.73,
    "reported_strategy": "Distressed",
    "num_investors": 208,
    "source": "ESMA"
  },
  {
    "fund_id": "PE023",
    "filing_type": "Form ADV",
    "filing_date": "2024-02-15",
    "filing_quarter": "2024-Q1",
    "reported_aum_millions": 1652.86,
    "reported_strategy": "Buyout",
    "num_investors": 113,
    "source": "ESMA"
  },
  {
    "fund_id": "PE034",
    "filing_type": "Form PF",
    "filing_date": "2024-09-15",
    "filing_quarter": "2024-Q3",
    "reported_aum_millions": 711.16,
    "reported_strategy": "Buyout",
    "num_investors": 66,
    "source": "ESMA"
  },
  {
    "fund_id": "HF022",
    "filing_type": "Form ADV",
    "filing_date": "2024-02-15",
    "filing_quarter": "2024-Q1",
    "reported_aum_millions": 12496.1,
    "reported_strategy": "Long/Short Equity",
    "num_investors": 319,
    "source": "SEC EDGAR"
  },
  {
    "fund_id": "HF022",
    "filing_type": "AIFMD",
    "filing_date": "2023-11-15",
    "filing_quarter": "2023-Q4",
    "reported_aum_millions": 14395.12,
    "reported_strategy": "Multi-Strategy",
    "num_investors": 447,
    "source": "SEC EDGAR"
  },
  {
    "fund_id": "PE048",
    "filing_type": "Form PF",
    "filing_date": "2024-02-15",
    "filing_quarter": "2024-Q1",
    "reported_aum_millions": 3791.53,
    "reported_strategy": "Mezzanine",
    "num_investors": 312,
    "source": "ESMA"
  },
  {
    "fund_id": "PE029",
    "filing_type": "Form PF",
    "filing_date": "2024-05-15",
    "filing_quarter": "2024-Q2",
    "reported_aum_millions": 3275.45,
    "reported_strategy": "Growth Equity",
    "num_investors": 136,
    "source": "ESMA"
  },
  {
    "fund_id": "PE029",
    "filing_type": "AIFMD",
    "filing_date": "2024-02-15",
    "filing_quarter": "2024-Q1",
    "reported_aum_millions": 3611.49,
    "reported_strategy": "Growth Equity",
    "num_investors": 494,
    "source": "SEC EDGAR"
  },
  {
    "fund_id": "VC013",
    "filing_type": "Form ADV",
    "filing_date": "2024-02-15",
    "filing_quarter": "2024-Q1",
    "reported_aum_millions": 1680.62,
    "reported_strategy": "Growth",
    "num_investors": 385,
    "source": "FCA"
  },
  {
    "fund_id": "VC025",
    "filing_type": "AIFMD",
    "filing_date": "2024-02-15",
    "filing_quarter": "2024-Q1",
    "reported_aum_millions": 1705.19,
    "reported_strategy": "Early Stage",
    "num_investors": 430,
    "source": "SEC EDGAR"
  },
  {
    "fund_id": "HF001",
    "filing_type": "Form PF",
    "filing_date": "2024-02-15",
    "filing_quarter": "2024-Q1",
    "reported_aum_millions": 8440.99,
    "reported_strategy": "Long/Short Equity",
    "num_investors": 364,
    "source": "FCA"
  },
  {
    "fund_id": "HF001",
    "filing_type": "Form ADV",
    "filing_date": "2024-02-15",
    "filing_quarter": "2024-Q1",
    "reported_aum_millions": 7767.52,
    "reported_strategy": "Growth Equity",
    "num_investors": 132,
    "source": "FCA"
  },
  {
    "fund_id": "HF045",
    "filing_type": "AIFMD",
    "filing_date": "2024-09-15",
    "filing_quarter": "2024-Q3",
    "reported_aum_millions": 2864.8,
    "reported_strategy": "Event Driven",
    "num_investors": 245,
    "source": "FCA"
  },
  {
    "fund_id": "HF010",
    "filing_type": "AIFMD",
    "filing_date": "2024-02-15",
    "filing_quarter": "2024-Q1",
    "reported_aum_millions": 6010.13,
    "reported_strategy": "Quantitative",
    "num_investors": 217,
    "source": "SEC EDGAR"
  },
  {
    "fund_id": "VC008",
    "filing_type": "AIFMD",
    "filing_date": "2024-02-15",
    "filing_quarter": "2024-Q1",
    "reported_aum_millions": 1880.12,
    "reported_strategy": "Growth",
    "num_investors": 46,
    "source": "ESMA"
  },
  {
    "fund_id": "VC008",
    "filing_type": "Form ADV",
    "filing_date": "2024-05-15",
    "filing_quarter": "2024-Q2",
    "reported_aum_millions": 1938.54,
    "reported_strategy": "Growth",
    "num_investors": 367,
    "source": "FCA"
  },
  {
    "fund_id": "PE010",
    "filing_type": "Form PF",
    "filing_date": "2024-09-15",
    "filing_quarter": "2024-Q3",
    "reported_aum_millions": 1550.71,
    "reported_strategy": "Distressed",
    "num_investors": 273,
    "source": "FCA"
  },
  {
    "fund_id": "HF007",
    "filing_type": "AIFMD",
    "filing_date": "2024-09-15",
    "filing_quarter": "2024-Q3",
    "reported_aum_millions": 6501.65,
    "reported_strategy": "Multi-Strategy",
    "num_investors": 30,
    "source": "ESMA"
  },
  {
    "fund_id": "HF007",
    "filing_type": "Form PF",
    "filing_date": "2024-05-15",
    "filing_quarter": "2024-Q2",
    "reported_aum_millions": 7627.62,
    "reported_strategy": "Seed",
    "num_investors": 297,
    "source": "FCA"
  },
  {
    "fund_id": "PE059",
    "filing_type": "Form PF",
    "filing_date": "2024-08-15",
    "filing_quarter": "2024-Q3",
    "reported_aum_millions": 960.06,
    "reported_strategy": "Mezzanine",
    "num_investors": 342,
    "source": "ESMA"
  },
  {
    "fund_id": "HF044",
    "filing_type": "AIFMD",
    "filing_date": "2024-08-15",
    "filing_quarter": "2024-Q3",
    "reported_aum_millions": 12752.67,
    "reported_strategy": "Seed",
    "num_investors": 358,
    "source": "ESMA"
  },
  {
    "fund_id": "PE036",
    "filing_type": "Form ADV",
    "filing_date": "2024-09-15",
    "filing_quarter": "2024-Q3",
    "reported_aum_millions": 1045.17,
    "reported_strategy": "Mezzanine",
    "num_investors": 266,
    "source": "FCA"
  },
  {
    "fund_id": "PE036",
    "filing_type": "AIFMD",
    "filing_date": "2024-09-15",
    "filing_quarter": "2024-Q3",
    "reported_aum_millions": 1196.68,
    "reported_strategy": "Mezzanine",
    "num_investors": 470,
    "source": "ESMA"
  },
  {
    "fund_id": "HF024",
    "filing_type": "AIFMD",
    "filing_date": "2023-11-15",
    "filing_quarter": "2023-Q4",
    "reported_aum_millions": 3476.41,
    "reported_strategy": "Long/Short Equity",
    "num_investors": 424,
    "source": "SEC EDGAR"
  },
  {
    "fund_id": "HF024",
    "filing_type": "Form PF",
    "filing_date": "2024-08-15",
    "filing_quarter": "2024-Q3",
    "reported_aum_millions": 3402.79,
    "reported_strategy": "Long/Short Equity",
    "num_investors": 210,
    "source": "SEC EDGAR"
  },
  {
    "fund_id": "PE055",
    "filing_type": "AIFMD",
    "filing_date": "2024-09-15",
    "filing_quarter": "2024-Q3",
    "reported_aum_millions": 3334.32,
    "reported_strategy": "Mezzanine",
    "num_investors": 85,
    "source": "ESMA"
  },
  {
    "fund_id": "PE055",
    "filing_type": "AIFMD",
    "filing_date": "2024-08-15",
    "filing_quarter": "2024-Q3",
    "reported_aum_millions": 3344.2,
    "reported_strategy": "Mezzanine",
    "num_investors": 21,
    "source": "ESMA"
  },
  {
    "fund_id": "HF014",
    "filing_type": "Form ADV",
    "filing_date": "2023-11-15",
    "filing_quarter": "2023-Q4",
    "reported_aum_millions": 2192.86,
    "reported_strategy": "Quantitative",
    "num_investors": 237,
    "source": "FCA"
  },
  {
    "fund_id": "HF014",
    "filing_type": "Form PF",
    "filing_date": "2024-09-15",
    "filing_quarter": "2024-Q3",
    "reported_aum_millions": 2102.51,
    "reported_strategy": "Quantitative",
    "num_investors": 437,
    "source": "FCA"
  },
  {
    "fund_id": "HF041",
    "filing_type": "Form ADV",
    "filing_date": "2024-02-15",
    "filing_quarter": "2024-Q1",
    "reported_aum_millions": 9709.61,
    "reported_strategy": "Global Macro",
    "num_investors": 258,
    "source": "FCA"
  },
  {
    "fund_id": "HF041",
    "filing_type": "Form ADV",
    "filing_date": "2023-11-15",
    "filing_quarter": "2023-Q4",
    "reported_aum_millions": 9508.35,
    "reported_strategy": "Global Macro",
    "num_investors": 300,
    "source": "SEC EDGAR"
  },
  {
    "fund_id": "HF011",
    "filing_type": "Form ADV",
    "filing_date": "2024-08-15",
    "filing_quarter": "2024-Q3",
    "reported_aum_millions": 5016.47,
    "reported_strategy": "Event Driven",
    "num_investors": 157,
    "source": "SEC EDGAR"
  },
  {
    "fund_id": "HF011",
    "filing_type": "Form PF",
    "filing_date": "2024-08-15",
    "filing_quarter": "2024-Q3",
    "reported_aum_millions": 5064.1,
    "reported_strategy": "Event Driven",
    "num_investors": 326,
    "source": "SEC EDGAR"
  },
  {
    "fund_id": "VC006",
    "filing_type": "AIFMD",
    "filing_date": "2024-08-15",
    "filing_quarter": "2024-Q3",
    "reported_aum_millions": 566.07,
    "reported_strategy": "Late Stage",
    "num_investors": 473,
    "source": "FCA"
  },
  {
    "fund_id": "VC006",
    "filing_type": "Form ADV",
    "filing_date": "2024-08-15",
    "filing_quarter": "2024-Q3",
    "reported_aum_millions": 379.7,
    "reported_strategy": "Late Stage",
    "num_investors": 304,
    "source": "SEC EDGAR"
  },
  {
    "fund_id": "VC029",
    "filing_type": "AIFMD",
    "filing_date": "2024-05-15",
    "filing_quarter": "2024-Q2",
    "reported_aum_millions": 1116.22,
    "reported_strategy": "Early Stage",
    "num_investors": 27,
    "source": "FCA"
  },
  {
    "fund_id": "VC029",
    "filing_type": "Form ADV",
    "filing_date": "2024-05-15",
    "filing_quarter": "2024-Q2",
    "reported_aum_millions": 1109.64,
    "reported_strategy": "Early Stage",
    "num_investors": 286,
    "source": "SEC EDGAR"
  },
  {
    "fund_id": "PE042",
    "filing_type": "Form ADV",
    "filing_date": "2024-09-15",
    "filing_quarter": "2024-Q3",
    "reported_aum_millions": 2429.46,
    "reported_strategy": "Distressed",
    "num_investors": 403,
    "source": "SEC EDGAR"
  },
  {
    "fund_id": "PE042",
    "filing_type": "AIFMD",
    "filing_date": "2024-02-15",
    "filing_quarter": "2024-Q1",
    "reported_aum_millions": 2368.5,
    "reported_strategy": "Event Driven",
    "num_investors": 289,
    "source": "FCA"
  },
  {
    "fund_id": "PE033",
    "filing_type": "AIFMD",
    "filing_date": "2024-05-15",
    "filing_quarter": "2024-Q2",
    "reported_aum_millions": 4653.47,
    "reported_strategy": "Mezzanine",
    "num_investors": 351,
    "source": "SEC EDGAR"
  },
  {
    "fund_id": "PE033",
    "filing_type": "Form ADV",
    "filing_date": "2023-11-15",
    "filing_quarter": "2023-Q4",
    "reported_aum_millions": 4954.1,
    "reported_strategy": "Mezzanine",
    "num_investors": 362,
    "source": "SEC EDGAR"
  },
  {
    "fund_id": "PE021",
    "filing_type": "Form ADV",
    "filing_date": "2024-09-15",
    "filing_quarter": "2024-Q3",
    "reported_aum_millions": 4393.96,
    "reported_strategy": "Distressed",
    "num_investors": 22,
    "source": "ESMA"
  },
  {
    "fund_id": "PE021",
    "filing_type": "Form PF",
    "filing_date": "2023-11-15",
    "filing_quarter": "2023-Q4",
    "reported_aum_millions": 4577.63,
    "reported_strategy": "Distressed",
    "num_investors": 177,
    "source": "SEC EDGAR"
  },
  {
    "fund_id": "HF025",
    "filing_type": "Form ADV",
    "filing_date": "2023-11-15",
    "filing_quarter": "2023-Q4",
    "reported_aum_millions": 14375.85,
    "reported_strategy": "Event Driven",
    "num_investors": 110,
    "source": "SEC EDGAR"
  },
  {
    "fund_id": "VC005",
    "filing_type": "Form PF",
    "filing_date": "2023-11-15",
    "filing_quarter": "2023-Q4",
    "reported_aum_millions": 1351.53,
    "reported_strategy": "Late Stage",
    "num_investors": 272,
    "source": "ESMA"
  },
  {
    "fund_id": "VC001",
    "filing_type": "Form PF",
    "filing_date": "2024-02-15",
    "filing_quarter": "2024-Q1",
    "reported_aum_millions": 1978.6,
    "reported_strategy": "Early Stage",
    "num_investors": 475,
    "source": "FCA"
  },
  {
    "fund_id": "HF035",
    "filing_type": "Form ADV",
    "filing_date": "2024-02-15",
    "filing_quarter": "2024-Q1",
    "reported_aum_millions": 7853.37,
    "reported_strategy": "Quantitative",
    "num_investors": 207,
    "source": "ESMA"
  },
  {
    "fund_id": "HF035",
    "filing_type": "Form ADV",
    "filing_date": "2024-09-15",
    "filing_quarter": "2024-Q3",
    "reported_aum_millions": 6029.91,
    "reported_strategy": "Quantitative",
    "num_investors": 457,
    "source": "FCA"
  },
  {
    "fund_id": "PE008",
    "filing_type": "Form ADV",
    "filing_date": "2024-08-15",
    "filing_quarter": "2024-Q3",
    "reported_aum_millions": -248.61,
    "reported_strategy": "Mezzanine",
    "num_investors": 421,
    "source": "ESMA"
  },
  {
    "fund_id": "PE049",
    "filing_type": "Form ADV",
    "filing_date": "2024-08-15",
    "filing_quarter": "2024-Q3",
    "reported_aum_millions": 4972.22,
    "reported_strategy": "Seed",
    "num_investors": 383,
    "source": "ESMA"
  },
  {
    "fund_id": "PE049",
    "filing_type": "Form PF",
    "filing_date": "2024-08-15",
    "filing_quarter": "2024-Q3",
    "reported_aum_millions": 4795.36,
    "reported_strategy": "Distressed",
    "num_investors": 116,
    "source": "ESMA"
  },
  {
    "fund_id": "VC024",
    "filing_type": "AIFMD",
    "filing_date": "2023-11-15",
    "filing_quarter": "2023-Q4",
    "reported_aum_millions": 1261.98,
    "reported_strategy": "Seed",
    "num_investors": 397,
    "source": "ESMA"
  },
  {
    "fund_id": "VC024",
    "filing_type": "Form ADV",
    "filing_date": "2024-09-15",
    "filing_quarter": "2024-Q3",
    "reported_aum_millions": 1465.71,
    "reported_strategy": "Seed",
    "num_investors": 222,
    "source": "SEC EDGAR"
  },
  {
    "fund_id": "PE043",
    "filing_type": "Form PF",
    "filing_date": "2023-11-15",
    "filing_quarter": "2023-Q4",
    "reported_aum_millions": 1113.12,
    "reported_strategy": "Distressed",
    "num_investors": 436,
    "source": "ESMA"
  },
  {
    "fund_id": "PE043",
    "filing_type": "Form ADV",
    "filing_date": "2024-05-15",
    "filing_quarter": "2024-Q2",
    "reported_aum_millions": 1102.19,
    "reported_strategy": "Long/Short Equity",
    "num_investors": 437,
    "source": "FCA"
  },
  {
    "fund_id": "VC033",
    "filing_type": "Form PF",
    "filing_date": "2024-02-15",
    "filing_quarter": "2024-Q1",
    "reported_aum_millions": 617.06,
    "reported_strategy": "Growth",
    "num_investors": 415,
    "source": "SEC EDGAR"
  },
  {
    "fund_id": "VC033",
    "filing_type": "AIFMD",
    "filing_date": "2024-08-15",
    "filing_quarter": "2024-Q3",
    "reported_aum_millions": 647.56,
    "reported_strategy": "Distressed",
    "num_investors": 251,
    "source": "SEC EDGAR"
  },
  {
    "fund_id": "VC031",
    "filing_type": "AIFMD",
    "filing_date": "2024-02-15",
    "filing_quarter": "2024-Q1",
    "reported_aum_millions": 1610.89,
    "reported_strategy": "Late Stage",
    "num_investors": 135,
    "source": "SEC EDGAR"
  },
  {
    "fund_id": "VC031",
    "filing_type": "Form PF",
    "filing_date": "2024-09-15",
    "filing_quarter": "2024-Q3",
    "reported_aum_millions": 1214.53,
    "reported_strategy": "Late Stage",
    "num_investors": 316,
    "source": "FCA"
  },
  {
    "fund_id": "HF026",
    "filing_type": "Form ADV",
    "filing_date": "2023-11-15",
    "filing_quarter": "2023-Q4",
    "reported_aum_millions": 12172.94,
    "reported_strategy": "Multi-Strategy",
    "num_investors": 331,
    "source": "FCA"
  },
  {
    "fund_id": "HF026",
    "filing_type": "Form ADV",
    "filing_date": "2024-02-15",
    "filing_quarter": "2024-Q1",
    "reported_aum_millions": 12641.19,
    "reported_strategy": "Multi-Strategy",
    "num_investors": 272,
    "source": "FCA"
  },
  {
    "fund_id": "VC016",
    "filing_type": "Form ADV",
    "filing_date": "2024-05-15",
    "filing_quarter": "2024-Q2",
    "reported_aum_millions": 352.67,
    "reported_strategy": "Late Stage",
    "num_investors": 246,
    "source": "FCA"
  },
  {
    "fund_id": "VC027",
    "filing_type": "Form ADV",
    "filing_date": "2024-05-15",
    "filing_quarter": "2024-Q2",
    "reported_aum_millions": 1166.61,
    "reported_strategy": "Seed",
    "num_investors": 335,
    "source": "ESMA"
  },
  {
    "fund_id": "VC023",
    "filing_type": "Form PF",
    "filing_date": "2024-05-15",
    "filing_quarter": "2024-Q2",
    "reported_aum_millions": 1167.29,
    "reported_strategy": "Late Stage",
    "num_investors": 273,
    "source": "SEC EDGAR"
  },
  {
    "fund_id": "PE063",
    "filing_type": "Form ADV",
    "filing_date": "2024-09-15",
    "filing_quarter": "2024-Q3",
    "reported_aum_millions": 2013.09,
    "reported_strategy": "Buyout",
    "num_investors": 456,
    "source": "ESMA"
  },
  {
    "fund_id": "VC032",
    "filing_type": "Form PF",
    "filing_date": "2024-05-15",
    "filing_quarter": "2024-Q2",
    "reported_aum_millions": 1632.12,
    "reported_strategy": "Seed",
    "num_investors": 283,
    "source": "FCA"
  },
  {
    "fund_id": "VC032",
    "filing_type": "AIFMD",
    "filing_date": "2024-05-15",
    "filing_quarter": "2024-Q2",
    "reported_aum_millions": 1523.92,
    "reported_strategy": "Seed",
    "num_investors": 154,
    "source": "ESMA"
  },
  {
    "fund_id": "HF004",
    "filing_type": "Form PF",
    "filing_date": "2024-02-15",
    "filing_quarter": "2024-Q1",
    "reported_aum_millions": 10813.04,
    "reported_strategy": "Global Macro",
    "num_investors": 121,
    "source": "SEC EDGAR"
  },
  {
    "fund_id": "HF004",
    "filing_type": "AIFMD",
    "filing_date": "2023-11-15",
    "filing_quarter": "2023-Q4",
    "reported_aum_millions": 7797.4,
    "reported_strategy": "Global Macro",
    "num_investors": 324,
    "source": "FCA"
  },
  {
    "fund_id": "PE051",
    "filing_type": "Form PF",
    "filing_date": "2024-02-15",
    "filing_quarter": "2024-Q1",
    "reported_aum_millions": 4289.33,
    "reported_strategy": "Multi-Strategy",
    "num_investors": 482,
    "source": "SEC EDGAR"
  },
  {
    "fund_id": "HF039",
    "filing_type": "Form ADV",
    "filing_date": "2024-05-15",
    "filing_quarter": "2024-Q2",
    "reported_aum_millions": 11987.53,
    "reported_strategy": "Long/Short Equity",
    "num_investors": 465,
    "source": "FCA"
  },
  {
    "fund_id": "HF039",
    "filing_type": "AIFMD",
    "filing_date": "2023-11-15",
    "filing_quarter": "2023-Q4",
    "reported_aum_millions": 11962.58,
    "reported_strategy": "Long/Short Equity",
    "num_investors": 165,
    "source": "SEC EDGAR"
  },
  {
    "fund_id": "HF008",
    "filing_type": "AIFMD",
    "filing_date": "2024-08-15",
    "filing_quarter": "2024-Q3",
    "reported_aum_millions": 8243.88,
    "reported_strategy": "Quantitative",
    "num_investors": 126,
    "source": "ESMA"
  },
  {
    "fund_id": "HF021",
    "filing_type": "AIFMD",
    "filing_date": "2024-08-15",
    "filing_quarter": "2024-Q3",
    "reported_aum_millions": 8538.85,
    "reported_strategy": "Multi-Strategy",
    "num_investors": 400,
    "source": "SEC EDGAR"
  },
  {
    "fund_id": "PE014",
    "filing_type": "Form PF",
    "filing_date": "2024-09-15",
    "filing_quarter": "2024-Q3",
    "reported_aum_millions": 2023.86,
    "reported_strategy": "Growth Equity",
    "num_investors": 110,
    "source": "SEC EDGAR"
  },
  {
    "fund_id": "PE019",
    "filing_type": "Form ADV",
    "filing_date": "2023-11-15",
    "filing_quarter": "2023-Q4",
    "reported_aum_millions": 3911.43,
    "reported_strategy": "Mezzanine",
    "num_investors": 32,
    "source": "SEC EDGAR"
  },
  {
    "fund_id": "PE070",
    "filing_type": "AIFMD",
    "filing_date": "2024-09-15",
    "filing_quarter": "2024-Q3",
    "reported_aum_millions": 2500.45,
    "reported_strategy": "Mezzanine",
    "num_investors": 115,
    "source": "FCA"
  },
  {
    "fund_id": "PE070",
    "filing_type": "Form PF",
    "filing_date": "2024-08-15",
    "filing_quarter": "2024-Q3",
    "reported_aum_millions": 2142.95,
    "reported_strategy": "Mezzanine",
    "num_investors": 84,
    "source": "FCA"
  },
  {
    "fund_id": "VC019",
    "filing_type": "AIFMD",
    "filing_date": "2023-11-15",
    "filing_quarter": "2023-Q4",
    "reported_aum_millions": 1119.5,
    "reported_strategy": "Early Stage",
    "num_investors": 409,
    "source": "FCA"
  },
  {
    "fund_id": "VC019",
    "filing_type": "Form PF",
    "filing_date": "2023-11-15",
    "filing_quarter": "2023-Q4",
    "reported_aum_millions": 1223.95,
    "reported_strategy": "Early Stage",
    "num_investors": 429,
    "source": "FCA"
  },
  {
    "fund_id": "PE028",
    "filing_type": "Form ADV",
    "filing_date": "2023-11-15",
    "filing_quarter": "2023-Q4",
    "reported_aum_millions": 385.69,
    "reported_strategy": "Growth Equity",
    "num_investors": 97,
    "source": "FCA"
  },
  {
    "fund_id": "HF019",
    "filing_type": "AIFMD",
    "filing_date": "2024-09-15",
    "filing_quarter": "2024-Q3",
    "reported_aum_millions": 2193.49,
    "reported_strategy": "Event Driven",
    "num_investors": 253,
    "source": "ESMA"
  },
  {
    "fund_id": "HF016",
    "filing_type": "Form ADV",
    "filing_date": "2024-02-15",
    "filing_quarter": "2024-Q1",
    "reported_aum_millions": 9814.09,
    "reported_strategy": "Global Macro",
    "num_investors": 204,
    "source": "ESMA"
  },
  {
    "fund_id": "HF043",
    "filing_type": "Form ADV",
    "filing_date": "2023-11-15",
    "filing_quarter": "2023-Q4",
    "reported_aum_millions": 3483.18,
    "reported_strategy": "Event Driven",
    "num_investors": 73,
    "source": "ESMA"
  },
  {
    "fund_id": "HF023",
    "filing_type": "AIFMD",
    "filing_date": "2023-11-15",
    "filing_quarter": "2023-Q4",
    "reported_aum_millions": 6480.38,
    "reported_strategy": "Long/Short Equity",
    "num_investors": 157,
    "source": "FCA"
  }
]